mcp_basecamp/__init__.py
mcp_basecamp/server.py
mcp_basecamp-0.0.2.dist-info/METADATA
mcp_basecamp-0.0.2.dist-info/WHEEL
mcp_basecamp-0.0.2.dist-info/entry_points.txt
mcp_basecamp-0.0.2.dist-info/top_level.txt
mcp_basecamp-0.0.2.dist-info/RECORD
