Metadata-Version: 2.4
Name: mcp-basecamp
Version: 0.0.2
Summary: MCP server for Basecamp integration
Project-URL: Homepage, https://github.com/user/mcp-basecamp
Project-URL: Bug Tracker, https://github.com/user/mcp-basecamp/issues
Requires-Python: >=3.10
Requires-Dist: mcp[cli]>=1.6.0
Requires-Dist: httpx>=0.24.0
